<?xml version="1.0"?>
<chromechecker>
  <time>2022-10-12 09:40:08</time>
  <stable32>
    <version>ELEMENT=actionATTRIBUTE=argumentsVALUE=--verbose-loggingATTRIBUTE=--channelVALUE=stableATTRIBUTE=eventVALUE=installATTRIBUTE=runVALUE=106.0.5249.119_chrome_installer.exe</version>
    <download>
      <url>https://www.google.com/dl/release2/chrome/adligqeuub6pghhs4zfp2xs4ca5q_106.0.5249.119/ENDpackages</url>
      <url>https://dl.google.com/release2/chrome/adligqeuub6pghhs4zfp2xs4ca5q_106.0.5249.119/ENDpackages</url>
      <url>https://106.0.5249.119ENDpackages</url>
    </download>
    <sha256>86233128</sha256>
    <size>ENDmanifest</size>
  </stable32>
  <stable64>
    <version>ELEMENT=actionATTRIBUTE=argumentsVALUE=--verbose-loggingATTRIBUTE=--channelVALUE=stableATTRIBUTE=eventVALUE=installATTRIBUTE=runVALUE=106.0.5249.119_chrome_installer.exe</version>
    <download>
      <url>https://www.google.com/dl/release2/chrome/gfu3lptcra3hizbjcq3dbfrdnq_106.0.5249.119/ENDpackages</url>
      <url>https://dl.google.com/release2/chrome/gfu3lptcra3hizbjcq3dbfrdnq_106.0.5249.119/ENDpackages</url>
      <url>https://106.0.5249.119ENDpackages</url>
    </download>
    <sha256>90580520</sha256>
    <size>ENDmanifest</size>
  </stable64>
  <beta32>
    <version>ELEMENT=actionATTRIBUTE=argumentsVALUE=--verbose-loggingATTRIBUTE=eventVALUE=installATTRIBUTE=runVALUE=107.0.5304.29_chrome_installer.exe</version>
    <download>
      <url>https://www.google.com/dl/release2/chrome/hmbzzlrcerjsr5uuhehjrss46m_107.0.5304.29/ENDpackages</url>
      <url>https://dl.google.com/release2/chrome/hmbzzlrcerjsr5uuhehjrss46m_107.0.5304.29/ENDpackages</url>
      <url>https://107.0.5304.29ENDpackages</url>
    </download>
    <sha256>88581160</sha256>
    <size>ENDmanifest</size>
  </beta32>
  <beta64>
    <version>ELEMENT=actionATTRIBUTE=argumentsVALUE=--verbose-loggingATTRIBUTE=eventVALUE=installATTRIBUTE=runVALUE=107.0.5304.29_chrome_installer.exe</version>
    <download>
      <url>https://www.google.com/dl/release2/chrome/adg6jfwqefkujtikfcmexha33oca_107.0.5304.29/ENDpackages</url>
      <url>https://dl.google.com/release2/chrome/adg6jfwqefkujtikfcmexha33oca_107.0.5304.29/ENDpackages</url>
      <url>https://107.0.5304.29ENDpackages</url>
    </download>
    <sha256>93133352</sha256>
    <size>ENDmanifest</size>
  </beta64>
  <dev32>
    <version>ELEMENT=actionATTRIBUTE=argumentsVALUE=--verbose-loggingATTRIBUTE=eventVALUE=installATTRIBUTE=runVALUE=108.0.5343.2_chrome_installer.exe</version>
    <download>
      <url>https://www.google.com/dl/release2/chrome/ci5u73ek7deaa3vr5w266szwyu_108.0.5343.2/ENDpackages</url>
      <url>https://dl.google.com/release2/chrome/ci5u73ek7deaa3vr5w266szwyu_108.0.5343.2/ENDpackages</url>
      <url>https://108.0.5343.2ENDpackages</url>
    </download>
    <sha256>88708136</sha256>
    <size>ENDmanifest</size>
  </dev32>
  <dev64>
    <version>ELEMENT=actionATTRIBUTE=argumentsVALUE=--verbose-loggingATTRIBUTE=eventVALUE=installATTRIBUTE=runVALUE=108.0.5343.2_chrome_installer.exe</version>
    <download>
      <url>https://www.google.com/dl/release2/chrome/myn2ldoxsjdym5grhcz2eo7zly_108.0.5343.2/ENDpackages</url>
      <url>https://dl.google.com/release2/chrome/myn2ldoxsjdym5grhcz2eo7zly_108.0.5343.2/ENDpackages</url>
      <url>https://108.0.5343.2ENDpackages</url>
    </download>
    <sha256>92369960</sha256>
    <size>ENDmanifest</size>
  </dev64>
  <canary32>
    <version>ELEMENT=actionATTRIBUTE=argumentsVALUE=--do-not-launch-chromeATTRIBUTE=eventVALUE=installATTRIBUTE=runVALUE=108.0.5354.2_chrome_installer.exe</version>
    <download>
      <url>https://www.google.com/dl/release2/chrome/adxskjhskwfquuovg62yaqsub4gq_108.0.5354.2/ENDpackages</url>
      <url>https://dl.google.com/release2/chrome/adxskjhskwfquuovg62yaqsub4gq_108.0.5354.2/ENDpackages</url>
      <url>https://108.0.5354.2ENDpackages</url>
    </download>
    <sha256>88688680</sha256>
    <size>ENDmanifest</size>
  </canary32>
  <canary64>
    <version>ELEMENT=actionATTRIBUTE=argumentsVALUE=--do-not-launch-chromeATTRIBUTE=eventVALUE=installATTRIBUTE=runVALUE=108.0.5354.2_chrome_installer.exe</version>
    <download>
      <url>https://www.google.com/dl/release2/chrome/admluegwsduad5iioxooimb3mi2q_108.0.5354.2/ENDpackages</url>
      <url>https://dl.google.com/release2/chrome/admluegwsduad5iioxooimb3mi2q_108.0.5354.2/ENDpackages</url>
      <url>https://108.0.5354.2ENDpackages</url>
    </download>
    <sha256>92422184</sha256>
    <size>ENDmanifest</size>
  </canary64>
  <stableapple>
    <version>ELEMENT=actionATTRIBUTE=argumentsVALUE=--verbose-loggingATTRIBUTE=--channelVALUE=stableATTRIBUTE=eventVALUE=installATTRIBUTE=runVALUE=106.0.5249.119_chrome_installer.exe</version>
    <download>
      <url>https://dl.google.com/chrome/mac/universal/stable/GGRO/googlechrome.dmg</url>
      <url>https://dl.google.com/chrome/mac/universal/stable/GGRO/googlechrome.dmg</url>
      <url>https://dl.google.com/chrome/mac/universal/stable/GGRO/googlechrome.dmg</url>
    </download>
    <sha256>86233128</sha256>
    <size>ENDmanifest</size>
  </stableapple>
  <stableintel>
    <version>ELEMENT=actionATTRIBUTE=argumentsVALUE=--verbose-loggingATTRIBUTE=--channelVALUE=stableATTRIBUTE=eventVALUE=installATTRIBUTE=runVALUE=106.0.5249.119_chrome_installer.exe</version>
    <download>
      <url>https://dl.google.com/chrome/mac/stable/GGRO/googlechrome.dmg</url>
      <url>https://dl.google.com/chrome/mac/stable/GGRO/googlechrome.dmg</url>
      <url>https://dl.google.com/chrome/mac/stable/GGRO/googlechrome.dmg</url>
    </download>
    <sha256>90580520</sha256>
    <size>ENDmanifest</size>
  </stableintel>
  <devapple>
    <version>ELEMENT=actionATTRIBUTE=argumentsVALUE=--verbose-loggingATTRIBUTE=eventVALUE=installATTRIBUTE=runVALUE=107.0.5304.29_chrome_installer.exe</version>
    <download>
      <url>https://dl.google.com/chrome/mac/universal/beta/googlechromebeta.dmg</url>
      <url>https://dl.google.com/chrome/mac/universal/beta/googlechromebeta.dmg</url>
      <url>https://dl.google.com/chrome/mac/universal/beta/googlechromebeta.dmg</url>
    </download>
    <sha256>88581160</sha256>
    <size>ENDmanifest</size>
  </devapple>
  <devintel>
    <version>ELEMENT=actionATTRIBUTE=argumentsVALUE=--verbose-loggingATTRIBUTE=eventVALUE=installATTRIBUTE=runVALUE=107.0.5304.29_chrome_installer.exe</version>
    <download>
      <url>https://dl.google.com/chrome/mac/beta/googlechromebeta.dmg</url>
      <url>https://dl.google.com/chrome/mac/beta/googlechromebeta.dmg</url>
      <url>https://dl.google.com/chrome/mac/beta/googlechromebeta.dmg</url>
    </download>
    <sha256>93133352</sha256>
    <size>ENDmanifest</size>
  </devintel>
  <devapple>
    <version>ELEMENT=actionATTRIBUTE=argumentsVALUE=--verbose-loggingATTRIBUTE=eventVALUE=installATTRIBUTE=runVALUE=108.0.5343.2_chrome_installer.exe</version>
    <download>
      <url>https://dl.google.com/chrome/mac/universal/dev/googlechromedev.dmg</url>
      <url>https://dl.google.com/chrome/mac/universal/dev/googlechromedev.dmg</url>
      <url>https://dl.google.com/chrome/mac/universal/dev/googlechromedev.dmg</url>
    </download>
    <sha256>88708136</sha256>
    <size>ENDmanifest</size>
  </devapple>
  <devintel>
    <version>ELEMENT=actionATTRIBUTE=argumentsVALUE=--verbose-loggingATTRIBUTE=eventVALUE=installATTRIBUTE=runVALUE=108.0.5343.2_chrome_installer.exe</version>
    <download>
      <url>https://dl.google.com/chrome/mac/dev/googlechromedev.dmg</url>
      <url>https://dl.google.com/chrome/mac/dev/googlechromedev.dmg</url>
      <url>https://dl.google.com/chrome/mac/dev/googlechromedev.dmg</url>
    </download>
    <sha256>92369960</sha256>
    <size>ENDmanifest</size>
  </devintel>
  <canaryapple>
    <version>ELEMENT=actionATTRIBUTE=argumentsVALUE=--do-not-launch-chromeATTRIBUTE=eventVALUE=installATTRIBUTE=runVALUE=108.0.5354.2_chrome_installer.exe</version>
    <download>
      <url>https://dl.google.com/chrome/mac/universal/canary/googlechromecanary.dmg</url>
      <url>https://dl.google.com/chrome/mac/universal/canary/googlechromecanary.dmg</url>
      <url>https://dl.google.com/chrome/mac/universal/canary/googlechromecanary.dmg</url>
    </download>
    <sha256>88688680</sha256>
    <size>ENDmanifest</size>
  </canaryapple>
  <canaryintel>
    <version>ELEMENT=actionATTRIBUTE=argumentsVALUE=--do-not-launch-chromeATTRIBUTE=eventVALUE=installATTRIBUTE=runVALUE=108.0.5354.2_chrome_installer.exe</version>
    <download>
      <url>https://dl.google.com/chrome/mac/canary/googlechromecanary.dmg</url>
      <url>https://dl.google.com/chrome/mac/canary/googlechromecanary.dmg</url>
      <url>https://dl.google.com/chrome/mac/canary/googlechromecanary.dmg</url>
    </download>
    <sha256>92422184</sha256>
    <size>ENDmanifest</size>
  </canaryintel>
</chromechecker>
