<?xml version="1.0"?>
<chromechecker>
  <time>2023-02-28 08:58:27</time>
  <stable32>
    <version>ELEMENT=actionATTRIBUTE=argumentsVALUE=--verbose-loggingATTRIBUTE=eventVALUE=installATTRIBUTE=runVALUE=109.0.5414.129_chrome_installer.exe</version>
    <download>
      <url>https://www.google.com/dl/release2/chrome/kr3ekrngooyu46qwruasnjsjey_109.0.5414.129/ENDpackages</url>
      <url>https://dl.google.com/release2/chrome/kr3ekrngooyu46qwruasnjsjey_109.0.5414.129/ENDpackages</url>
      <url>https://109.0.5414.129ENDpackages</url>
    </download>
    <sha256>89269288</sha256>
    <size>ENDmanifest</size>
  </stable32>
  <stable64>
    <version>ELEMENT=actionATTRIBUTE=argumentsVALUE=--verbose-loggingATTRIBUTE=eventVALUE=installATTRIBUTE=runVALUE=109.0.5414.129_chrome_installer.exe</version>
    <download>
      <url>https://www.google.com/dl/release2/chrome/juzaykgd5e6nyvk27fwtbrjgoa_109.0.5414.129/ENDpackages</url>
      <url>https://dl.google.com/release2/chrome/juzaykgd5e6nyvk27fwtbrjgoa_109.0.5414.129/ENDpackages</url>
      <url>https://109.0.5414.129ENDpackages</url>
    </download>
    <sha256>93127208</sha256>
    <size>ENDmanifest</size>
  </stable64>
  <beta32>
    <version>ELEMENT=actionATTRIBUTE=argumentsVALUE=--verbose-loggingATTRIBUTE=eventVALUE=installATTRIBUTE=runVALUE=109.0.5414.74_chrome_installer.exe</version>
    <download>
      <url>https://www.google.com/dl/release2/chrome/adoealnpcgv3cubjcxakqpenftta_109.0.5414.74/ENDpackages</url>
      <url>https://dl.google.com/release2/chrome/adoealnpcgv3cubjcxakqpenftta_109.0.5414.74/ENDpackages</url>
      <url>https://109.0.5414.74ENDpackages</url>
    </download>
    <sha256>89243176</sha256>
    <size>ENDmanifest</size>
  </beta32>
  <beta64>
    <version>ELEMENT=actionATTRIBUTE=argumentsVALUE=--verbose-loggingATTRIBUTE=eventVALUE=installATTRIBUTE=runVALUE=109.0.5414.74_chrome_installer.exe</version>
    <download>
      <url>https://www.google.com/dl/release2/chrome/acdsghvjesmrml7w762mxzpadfxq_109.0.5414.74/ENDpackages</url>
      <url>https://dl.google.com/release2/chrome/acdsghvjesmrml7w762mxzpadfxq_109.0.5414.74/ENDpackages</url>
      <url>https://109.0.5414.74ENDpackages</url>
    </download>
    <sha256>93163560</sha256>
    <size>ENDmanifest</size>
  </beta64>
  <dev32>
    <version>ELEMENT=actionATTRIBUTE=argumentsVALUE=--verbose-loggingATTRIBUTE=eventVALUE=installATTRIBUTE=runVALUE=109.0.5414.25_chrome_installer.exe</version>
    <download>
      <url>https://www.google.com/dl/release2/chrome/admanswqr3s56dlrbigmegd2nbva_109.0.5414.25/ENDpackages</url>
      <url>https://dl.google.com/release2/chrome/admanswqr3s56dlrbigmegd2nbva_109.0.5414.25/ENDpackages</url>
      <url>https://109.0.5414.25ENDpackages</url>
    </download>
    <sha256>89239592</sha256>
    <size>ENDmanifest</size>
  </dev32>
  <dev64>
    <version>ELEMENT=actionATTRIBUTE=argumentsVALUE=--verbose-loggingATTRIBUTE=eventVALUE=installATTRIBUTE=runVALUE=109.0.5414.25_chrome_installer.exe</version>
    <download>
      <url>https://www.google.com/dl/release2/chrome/ads2hzefmr2xotvcwhl3irv6zziq_109.0.5414.25/ENDpackages</url>
      <url>https://dl.google.com/release2/chrome/ads2hzefmr2xotvcwhl3irv6zziq_109.0.5414.25/ENDpackages</url>
      <url>https://109.0.5414.25ENDpackages</url>
    </download>
    <sha256>93140520</sha256>
    <size>ENDmanifest</size>
  </dev64>
  <canary32>
    <version/>
    <download>
      <url>https://</url>
      <url>https://</url>
      <url>https://</url>
    </download>
    <sha256/>
    <size/>
  </canary32>
  <canary64>
    <version/>
    <download>
      <url>https://</url>
      <url>https://</url>
      <url>https://</url>
    </download>
    <sha256/>
    <size/>
  </canary64>
  <stableapple>
    <version>ELEMENT=actionATTRIBUTE=argumentsVALUE=--verbose-loggingATTRIBUTE=eventVALUE=installATTRIBUTE=runVALUE=109.0.5414.129_chrome_installer.exe</version>
    <download>
      <url>https://dl.google.com/chrome/mac/universal/stable/GGRO/googlechrome.dmg</url>
      <url>https://dl.google.com/chrome/mac/universal/stable/GGRO/googlechrome.dmg</url>
      <url>https://dl.google.com/chrome/mac/universal/stable/GGRO/googlechrome.dmg</url>
    </download>
    <sha256>89269288</sha256>
    <size>ENDmanifest</size>
  </stableapple>
  <stableintel>
    <version>ELEMENT=actionATTRIBUTE=argumentsVALUE=--verbose-loggingATTRIBUTE=eventVALUE=installATTRIBUTE=runVALUE=109.0.5414.129_chrome_installer.exe</version>
    <download>
      <url>https://dl.google.com/chrome/mac/stable/GGRO/googlechrome.dmg</url>
      <url>https://dl.google.com/chrome/mac/stable/GGRO/googlechrome.dmg</url>
      <url>https://dl.google.com/chrome/mac/stable/GGRO/googlechrome.dmg</url>
    </download>
    <sha256>93127208</sha256>
    <size>ENDmanifest</size>
  </stableintel>
  <devapple>
    <version>ELEMENT=actionATTRIBUTE=argumentsVALUE=--verbose-loggingATTRIBUTE=eventVALUE=installATTRIBUTE=runVALUE=109.0.5414.74_chrome_installer.exe</version>
    <download>
      <url>https://dl.google.com/chrome/mac/universal/beta/googlechromebeta.dmg</url>
      <url>https://dl.google.com/chrome/mac/universal/beta/googlechromebeta.dmg</url>
      <url>https://dl.google.com/chrome/mac/universal/beta/googlechromebeta.dmg</url>
    </download>
    <sha256>89243176</sha256>
    <size>ENDmanifest</size>
  </devapple>
  <devintel>
    <version>ELEMENT=actionATTRIBUTE=argumentsVALUE=--verbose-loggingATTRIBUTE=eventVALUE=installATTRIBUTE=runVALUE=109.0.5414.74_chrome_installer.exe</version>
    <download>
      <url>https://dl.google.com/chrome/mac/beta/googlechromebeta.dmg</url>
      <url>https://dl.google.com/chrome/mac/beta/googlechromebeta.dmg</url>
      <url>https://dl.google.com/chrome/mac/beta/googlechromebeta.dmg</url>
    </download>
    <sha256>93163560</sha256>
    <size>ENDmanifest</size>
  </devintel>
  <devapple>
    <version>ELEMENT=actionATTRIBUTE=argumentsVALUE=--verbose-loggingATTRIBUTE=eventVALUE=installATTRIBUTE=runVALUE=109.0.5414.25_chrome_installer.exe</version>
    <download>
      <url>https://dl.google.com/chrome/mac/universal/dev/googlechromedev.dmg</url>
      <url>https://dl.google.com/chrome/mac/universal/dev/googlechromedev.dmg</url>
      <url>https://dl.google.com/chrome/mac/universal/dev/googlechromedev.dmg</url>
    </download>
    <sha256>89239592</sha256>
    <size>ENDmanifest</size>
  </devapple>
  <devintel>
    <version>ELEMENT=actionATTRIBUTE=argumentsVALUE=--verbose-loggingATTRIBUTE=eventVALUE=installATTRIBUTE=runVALUE=109.0.5414.25_chrome_installer.exe</version>
    <download>
      <url>https://dl.google.com/chrome/mac/dev/googlechromedev.dmg</url>
      <url>https://dl.google.com/chrome/mac/dev/googlechromedev.dmg</url>
      <url>https://dl.google.com/chrome/mac/dev/googlechromedev.dmg</url>
    </download>
    <sha256>93140520</sha256>
    <size>ENDmanifest</size>
  </devintel>
  <canaryapple>
    <version>dl.google.com/chrome/mac/universal/canary/</version>
    <download>
      <url>https://</url>
      <url>https://</url>
      <url>https://</url>
    </download>
    <sha256>googlechromecanary.dmg</sha256>
    <size/>
  </canaryapple>
  <canaryintel>
    <version>dl.google.com/chrome/mac/canary/</version>
    <download>
      <url>https://</url>
      <url>https://</url>
      <url>https://</url>
    </download>
    <sha256>googlechromecanary.dmg</sha256>
    <size/>
  </canaryintel>
</chromechecker>
